rovibrational_excitation/__init__.py
rovibrational_excitation/cli/optimize.py
rovibrational_excitation/core/basis/__init__.py
rovibrational_excitation/core/basis/base.py
rovibrational_excitation/core/basis/hamiltonian.py
rovibrational_excitation/core/basis/linmol.py
rovibrational_excitation/core/basis/states.py
rovibrational_excitation/core/basis/symtop.py
rovibrational_excitation/core/basis/twolevel.py
rovibrational_excitation/core/basis/viblad.py
rovibrational_excitation/core/electric_field/__init__.py
rovibrational_excitation/core/electric_field/core.py
rovibrational_excitation/core/electric_field/envelopes.py
rovibrational_excitation/core/electric_field/modulation.py
rovibrational_excitation/core/nondimensional/__init__.py
rovibrational_excitation/core/nondimensional/analysis.py
rovibrational_excitation/core/nondimensional/converter.py
rovibrational_excitation/core/nondimensional/impl.py
rovibrational_excitation/core/nondimensional/scales.py
rovibrational_excitation/core/nondimensional/strategies.py
rovibrational_excitation/core/nondimensional/utils.py
rovibrational_excitation/core/propagation/__init__.py
rovibrational_excitation/core/propagation/base.py
rovibrational_excitation/core/propagation/factory.py
rovibrational_excitation/core/propagation/liouville.py
rovibrational_excitation/core/propagation/mixed_state.py
rovibrational_excitation/core/propagation/schrodinger.py
rovibrational_excitation/core/propagation/utils.py
rovibrational_excitation/core/propagation/algorithms/__init__.py
rovibrational_excitation/core/propagation/algorithms/rk4/__init__.py
rovibrational_excitation/core/propagation/algorithms/rk4/lvne.py
rovibrational_excitation/core/propagation/algorithms/rk4/schrodinger.py
rovibrational_excitation/core/propagation/algorithms/split_operator/__init__.py
rovibrational_excitation/core/propagation/algorithms/split_operator/schrodinger.py
rovibrational_excitation/core/units/__init__.py
rovibrational_excitation/core/units/constants.py
rovibrational_excitation-0.2.9.dist-info/licenses/LICENSE
rovibrational_excitation-0.2.9.dist-info/METADATA
rovibrational_excitation-0.2.9.dist-info/WHEEL
rovibrational_excitation-0.2.9.dist-info/top_level.txt
rovibrational_excitation-0.2.9.dist-info/RECORD
